{
	"$schema": "schemas/special_weapon.json",
	"type": 3,
	"name": "ma75b",
	"fireRate" : 5.0,
	"bullets" : 52,
	"ammo" : 0,
	"maxBullets" : 52,
	"damage" : 25,
	"reloadSpeed" : 1.5,
	"randomness" : true,
	"spreadPattern" : [],
	"spreadMultiplier" : 0,
	"projectileIndex" : 0,
	"defaultZoomFOV": 90,
	"zoomLevels": [ 60, 30 ],
	"range" : 250,
	"primaryFireMode" : 1,
	"specialType" : 2,
	"secondaryFireMode" : 2,
	"secondaryFireRate" : 1.2,
	"secondaryDamage" : 25,
	"secondaryBullets" : 7,
	"secondaryAmmo" : 300,
	"secondaryMaxBullets" : 7,
	"secondaryReloadSpeed" : 2.0,
	"secondaryRandomness" : 0,
	"secondarySpreadPattern" : [],
	"secondarySpreadMultiplier" : 0,
	"secondaryProjectileIndex" : 2,
	"secondaryRange" : 250,
	"randomSpread" : [0.5,0.8],
	"usesSecondaryAmmo" : true,
	"secondaryRandomSpread" : [0.0,0.0],
	"primaryModifierType" : "None",
	"secondaryModifierType" : "None",
	"primaryModifierTimer" : 0,
	"secondaryModifierTimer" : 0
}
